cibc/__init__.py
cibc/banking.py
cibc/data.py
cibc/test.py
cibc-0.3.5.dist-info/LICENSE.txt
cibc-0.3.5.dist-info/METADATA
cibc-0.3.5.dist-info/WHEEL
cibc-0.3.5.dist-info/top_level.txt
cibc-0.3.5.dist-info/RECORD
