Metadata-Version: 2.1
Name: cibc
Version: 0.3.5
Summary: Client library to support the Canadian Imperial Bank of Canadas API
Home-page: https://github.com/louismillette/CIBC
Author: Louis Millette
Author-email: louismillette1@gmail.com
License: MIT
Platform: UNKNOWN
Requires-Dist: requests
